lib2to3/__init__.py
lib2to3/pytree.py
mff_lib2to3_fake-0.1.0.dist-info/WHEEL
mff_lib2to3_fake-0.1.0.dist-info/METADATA
mff_lib2to3_fake-0.1.0.dist-info/RECORD
